pyuniswap/__init__.py
pyuniswap/pyuniswap.py
pyuniswap/abi_files/erc20.abi
pyuniswap/abi_files/router.abi
pyuniswap-1.0.0.dist-info/LICENSE
pyuniswap-1.0.0.dist-info/METADATA
pyuniswap-1.0.0.dist-info/WHEEL
pyuniswap-1.0.0.dist-info/top_level.txt
pyuniswap-1.0.0.dist-info/RECORD
