Metadata-Version: 2.1
Name: pyuniswap
Version: 1.0.0
Summary: An open source Python wrapper for Uniswap V2
Home-page: https://github.com/yyy20119/pyuniswap
Author: yyy20119
Author-email: 1508974340@qq.com
License: UNKNOWN
Platform: UNKNOWN
Classifier: Programming Language :: Python :: 3
Classifier: License :: OSI Approved :: MIT License
Classifier: Operating System :: OS Independent
Requires-Python: >=3.6
Requires-Dist: web3
